gitbaba/__init__.py
gitbaba/cli.py
gitbaba2-0.1.2.dist-info/licenses/LICENSE
gitbaba2-0.1.2.dist-info/METADATA
gitbaba2-0.1.2.dist-info/WHEEL
gitbaba2-0.1.2.dist-info/entry_points.txt
gitbaba2-0.1.2.dist-info/top_level.txt
gitbaba2-0.1.2.dist-info/RECORD
