Metadata-Version: 2.4
Name: gitbaba2
Version: 0.1.2
Summary: A lightweight CLI tool to simplify GitHub workflows. With GitBaba you can push local projects, create new repositories, delete repos, and manage authentication without typing long Git or GitHub commands. Perfect for developers who want a faster shortcut to manage GitHub projects.
Home-page: https://github.com/BotolMehedi/gitbaba
Author: BotolMehedi
Author-email: BotolMehedi <hellp@mehedi.fun>
License: MIT
Keywords: git,github,cli,automation,gitbaba
Classifier: Programming Language :: Python :: 3
Classifier: License :: OSI Approved :: MIT License
Classifier: Operating System :: OS Independent
Classifier: Environment :: Console
Classifier: Topic :: Utilities
License-File: LICENSE
Requires-Dist: requests>=2.28.0
Requires-Dist: colorama>=0.4.6
Dynamic: author
Dynamic: home-page
Dynamic: license-file
